BeeHiveOptimization/Beehive.py
BeeHiveOptimization/__init__.py
BeeHiveOptimization/base_init_methods.py
BeeHiveOptimization/base_test_functions.py
BeeHiveOptimization-1.1.0.dist-info/LICENSE.txt
BeeHiveOptimization-1.1.0.dist-info/METADATA
BeeHiveOptimization-1.1.0.dist-info/WHEEL
BeeHiveOptimization-1.1.0.dist-info/top_level.txt
BeeHiveOptimization-1.1.0.dist-info/RECORD
