Metadata-Version: 2.1
Name: BeeHiveOptimization
Version: 1.1.0
Summary: Implementation of beehive method (particle swarm optimization) for global optimization of multidimentional functions
Home-page: https://github.com/PasaOpasen/BeehiveMethod
Author: Demetry Pascal
Author-email: qtckpuhdsa@gmail.com
License: MIT
Keywords: beehive_method,optimization,function-optimization,stochastic-optimization,swarm particle,particle swarm optimization
Platform: UNKNOWN
Classifier: Development Status :: 4 - Beta
Classifier: Intended Audience :: Developers
Classifier: Topic :: Software Development :: Build Tools
Classifier: License :: OSI Approved :: MIT License
Classifier: Programming Language :: Python :: 3
Classifier: Programming Language :: Python :: 3.6
Classifier: Programming Language :: Python :: 3.7
Classifier: Programming Language :: Python :: 3.8
Requires-Dist: joblib
Requires-Dist: numpy
